configcalc/__init__.py
configcalc/config_merge.py
configcalc/parsers.py
configcalc/perform_calcs.py
configcalc/read_cfg_file.py
configcalc/utils.py
configcalc-0.1.2.dist-info/METADATA
configcalc-0.1.2.dist-info/WHEEL
configcalc-0.1.2.dist-info/licenses/LICENSE
configcalc-0.1.2.dist-info/RECORD
