Metadata-Version: 2.4
Name: configcalc
Version: 0.1.2
Summary: The purpose is to offer config files functionality with calculations that can be specified
Author-email: Raphael Proux <raphaelproux@gmail.com>
License-File: LICENSE
Requires-Python: >=3.11
Requires-Dist: pyparsing>=3.2.1
